examples/__init__.py
examples/hardware_data_ready.py
examples/simple.py
lsm9ds1_rjg/__init__.py
lsm9ds1_rjg/abstract_interrupt.py
lsm9ds1_rjg/abstract_transport.py
lsm9ds1_rjg/ag_status.py
lsm9ds1_rjg/driver.py
lsm9ds1_rjg/gpio_interrupt.py
lsm9ds1_rjg/i2c_transport.py
lsm9ds1_rjg/magnetometer_status.py
lsm9ds1_rjg/spi_transport.py
lsm9ds1_rjg/test_ag_status.py
test/__init__.py
test/test_ag_status.py
test/test_driver.py
test/test_magnetometer_status.py
lsm9ds1_rjg-1.0.0.dist-info/LICENSE.txt
lsm9ds1_rjg-1.0.0.dist-info/METADATA
lsm9ds1_rjg-1.0.0.dist-info/WHEEL
lsm9ds1_rjg-1.0.0.dist-info/top_level.txt
lsm9ds1_rjg-1.0.0.dist-info/RECORD
