Metadata-Version: 2.1
Name: lsm9ds1-rjg
Version: 1.0.0
Summary: A python module to enable a Raspberry Pi to access an LSM9DS1 IMU sensor.
Home-page: https://github.com/Richard-Gemmell/lsm9ds1-rjg
Author: Richard Gemmell
Author-email: 16683467+Richard-Gemmell@users.noreply.github.com
License: LICENSE.txt
Classifier: Programming Language :: Python :: 3.7
Classifier: License :: OSI Approved :: MIT License
Classifier: Operating System :: OS Independent
Classifier: Topic :: Software Development :: Embedded Systems
Classifier: Topic :: System :: Hardware :: Hardware Drivers
License-File: LICENSE.txt
Requires-Dist: smbus2 >=0.4.0
Requires-Dist: spidev >=3.2
